content_dedup/__init__.py
content_dedup/cli.py
content_dedup/config/__init__.py
content_dedup/config/field_mapping.py
content_dedup/config/field_mapping_balanced.py
content_dedup/config/field_mapping_minimal.py
content_dedup/config/settings.py
content_dedup/core/__init__.py
content_dedup/core/clustering.py
content_dedup/core/deduplicator.py
content_dedup/core/models_flexible.py
content_dedup/processors/__init__.py
content_dedup/processors/base.py
content_dedup/processors/language.py
content_dedup/processors/similarity.py
content_dedup/utils/__init__.py
content_dedup/utils/io.py
content_dedup/utils/migration.py
content_dedup/utils/progress.py
content_dedup/utils/validators.py
content_dedup-1.1.2.dist-info/licenses/LICENSE
tests/__init__.py
tests/conftest.py
tests/test_cli.py
tests/test_cli_enhanced.py
tests/test_cli_mapping_types.py
tests/test_clustering.py
tests/test_deduplicator.py
tests/test_field_mapping.py
tests/test_field_mapping_comparison.py
tests/test_integration.py
tests/test_language_processor.py
tests/test_models_flexible.py
tests/test_utils.py
content_dedup-1.1.2.dist-info/METADATA
content_dedup-1.1.2.dist-info/WHEEL
content_dedup-1.1.2.dist-info/entry_points.txt
content_dedup-1.1.2.dist-info/top_level.txt
content_dedup-1.1.2.dist-info/RECORD
