Metadata-Version: 2.4
Name: content-dedup
Version: 1.1.2
Summary: Intelligent content deduplication and clustering toolkit with multilingual support
Home-page: https://github.com/changyy/py-content-dedup
Author: changyy
Author-email: changyy.csie@gmail.com
License: MIT
Project-URL: Bug Tracker, https://github.com/changyy/py-content-dedup/issues
Project-URL: Documentation, https://github.com/changyy/py-content-dedup/docs
Project-URL: Repository, https://github.com/changyy/py-content-dedup
Project-URL: Changelog, https://github.com/changyy/py-content-dedup/blob/main/CHANGELOG.md
Keywords: deduplication clustering nlp content-analysis text-mining multilingual chinese english mixed-language
Classifier: Development Status :: 4 - Beta
Classifier: Intended Audience :: Developers
Classifier: Intended Audience :: Science/Research
Classifier: Operating System :: OS Independent
Classifier: Programming Language :: Python :: 3
Classifier: Programming Language :: Python :: 3.8
Classifier: Programming Language :: Python :: 3.9
Classifier: Programming Language :: Python :: 3.10
Classifier: Programming Language :: Python :: 3.11
Classifier: Programming Language :: Python :: 3.12
Classifier: Topic :: Text Processing :: Linguistic
Classifier: Topic :: Scientific/Engineering :: Artificial Intelligence
Classifier: Topic :: Software Development :: Libraries :: Python Modules
Classifier: Topic :: Software Development :: Libraries :: Python Modules
Classifier: Natural Language :: Chinese (Traditional)
Classifier: Natural Language :: Chinese (Simplified)
Classifier: Natural Language :: English
Requires-Python: >=3.8
License-File: LICENSE
Requires-Dist: scikit-learn>=1.0.0
Requires-Dist: numpy>=1.20.0
Requires-Dist: jieba>=0.42.0
Provides-Extra: dev
Requires-Dist: pytest>=6.0; extra == "dev"
Requires-Dist: pytest-cov>=3.0.0; extra == "dev"
Requires-Dist: black>=22.0.0; extra == "dev"
Requires-Dist: flake8>=4.0.0; extra == "dev"
Requires-Dist: mypy>=0.950; extra == "dev"
Requires-Dist: coverage>=6.0.0; extra == "dev"
Requires-Dist: pre-commit>=2.15.0; extra == "dev"
Provides-Extra: full
Requires-Dist: jieba>=0.42.0; extra == "full"
Requires-Dist: langdetect>=1.0.9; extra == "full"
Requires-Dist: nltk>=3.7.0; extra == "full"
Provides-Extra: chinese
Requires-Dist: jieba>=0.42.0; extra == "chinese"
Provides-Extra: langdetect
Requires-Dist: langdetect>=1.0.9; extra == "langdetect"
Provides-Extra: english
Requires-Dist: nltk>=3.7.0; extra == "english"
Provides-Extra: all
Requires-Dist: flake8>=4.0.0; extra == "all"
Requires-Dist: pre-commit>=2.15.0; extra == "all"
Requires-Dist: pytest>=6.0; extra == "all"
Requires-Dist: mypy>=0.950; extra == "all"
Requires-Dist: pytest-cov>=3.0.0; extra == "all"
Requires-Dist: jieba>=0.42.0; extra == "all"
Requires-Dist: langdetect>=1.0.9; extra == "all"
Requires-Dist: black>=22.0.0; extra == "all"
Requires-Dist: nltk>=3.7.0; extra == "all"
Requires-Dist: coverage>=6.0.0; extra == "all"
Dynamic: author
Dynamic: author-email
Dynamic: classifier
Dynamic: description
Dynamic: description-content-type
Dynamic: home-page
Dynamic: keywords
Dynamic: license
Dynamic: license-file
Dynamic: project-url
Dynamic: provides-extra
Dynamic: requires-dist
Dynamic: requires-python
Dynamic: summary
